yunchi/quote.cpython-38-x86_64-linux-gnu.so
yunchi/api.py
yunchi/data.cpython-38-x86_64-linux-gnu.so
yunchi/trade.cpython-38-x86_64-linux-gnu.so
yunchi/strategy.cpython-38-x86_64-linux-gnu.so
yunchi/model.py
yunchi/__init__.py
yunchi/pb/api_pb2.py
yunchi/pb/Quotation.proto
yunchi/pb/dtp.api.proto
yunchi/pb/Quotation_pb2.py
yunchi/pb/dtp.type.proto
yunchi/pb/type_pb2.py
yunchi/pb/__init__.py
yunchi-1.0.8.dist-info/RECORD
yunchi-1.0.8.dist-info/METADATA
yunchi-1.0.8.dist-info/WHEEL
yunchi-1.0.8.dist-info/top_level.txt
