Metadata-Version: 2.1
Name: yunchi
Version: 1.0.8
Summary: YunChi SDK
Author: dwzx
Author-email: yunchi@idwzx.com
Classifier: Programming Language :: Python
Classifier: Programming Language :: Python :: 3.8
Requires-Dist: six (==1.16.0)
Requires-Dist: websocket-client (==1.2.3)
Requires-Dist: protobuf (==3.17.3)
Requires-Dist: pyzmq (==19.0.2)
Requires-Dist: requests (==2.26.0)
Requires-Dist: cachetools (==4.2.4)
Requires-Dist: pandas (==1.4.3)
